django_pgschemas/__init__.py
django_pgschemas/apps.py
django_pgschemas/checks.py
django_pgschemas/clone_schema.gz
django_pgschemas/log.py
django_pgschemas/models.py
django_pgschemas/py.typed
django_pgschemas/routers.py
django_pgschemas/schema.py
django_pgschemas/settings.py
django_pgschemas/signals.py
django_pgschemas/utils.py
django_pgschemas/contrib/__init__.py
django_pgschemas/contrib/cache.py
django_pgschemas/contrib/channels.py
django_pgschemas/contrib/storage.py
django_pgschemas/management/__init__.py
django_pgschemas/management/commands/__init__.py
django_pgschemas/management/commands/_executors.py
django_pgschemas/management/commands/cloneschema.py
django_pgschemas/management/commands/createrefschema.py
django_pgschemas/management/commands/migrate.py
django_pgschemas/management/commands/migrateschema.py
django_pgschemas/management/commands/runschema.py
django_pgschemas/management/commands/whowill.py
django_pgschemas/postgresql/__init__.py
django_pgschemas/postgresql/_constraints.py
django_pgschemas/postgresql/base.py
django_pgschemas/postgresql/introspection.py
django_pgschemas/routing/__init__.py
django_pgschemas/routing/info.py
django_pgschemas/routing/middleware.py
django_pgschemas/routing/models.py
django_pgschemas/routing/urlresolvers.py
django_pgschemas-1.2.0.dist-info/METADATA
django_pgschemas-1.2.0.dist-info/WHEEL
django_pgschemas-1.2.0.dist-info/licenses/LICENSE
django_pgschemas-1.2.0.dist-info/RECORD
