Metadata-Version: 2.4
Name: django-pgschemas
Version: 1.2.0
Summary: Django multi-tenancy through Postgres schemas
Project-URL: repository, https://github.com/lorinkoz/django-pgschemas
Project-URL: documentation, https://django-pgschemas.readthedocs.io/
Author-email: Lorenzo Peña <lorinkoz@gmail.com>
License: MIT
License-File: LICENSE
Keywords: django,multi-tenancy,postgres,schemas,tenants
Classifier: Development Status :: 5 - Production/Stable
Classifier: Framework :: Django
Classifier: Framework :: Django :: 5.2
Classifier: Framework :: Django :: 6.0
Requires-Python: >=3.12
Requires-Dist: django>=5.2
